{
  "generated_at": "2026-03-20T12:07:49.102252+00:00",
  "record_key": "03-20",
  "top_5_hot": [
    {
      "city": "Honolulu",
      "state": "HI",
      "temp_f": 75.4,
      "lat": 21.307,
      "lon": -157.858
    },
    {
      "city": "Phoenix",
      "state": "AZ",
      "temp_f": 69.0,
      "lat": 33.448,
      "lon": -112.074
    },
    {
      "city": "Boise",
      "state": "ID",
      "temp_f": 57.6,
      "lat": 43.618,
      "lon": -116.202
    },
    {
      "city": "Oklahoma City",
      "state": "OK",
      "temp_f": 57.3,
      "lat": 35.468,
      "lon": -97.516
    },
    {
      "city": "Austin",
      "state": "TX",
      "temp_f": 57.2,
      "lat": 30.267,
      "lon": -97.743
    }
  ],
  "top_5_cold": [
    {
      "city": "Montpelier",
      "state": "VT",
      "temp_f": 27.5,
      "lat": 44.26,
      "lon": -72.575
    },
    {
      "city": "Augusta",
      "state": "ME",
      "temp_f": 27.8,
      "lat": 44.307,
      "lon": -69.782
    },
    {
      "city": "Juneau",
      "state": "AK",
      "temp_f": 29.0,
      "lat": 58.301,
      "lon": -134.42
    },
    {
      "city": "Concord",
      "state": "NH",
      "temp_f": 29.9,
      "lat": 43.208,
      "lon": -71.538
    },
    {
      "city": "Albany",
      "state": "NY",
      "temp_f": 30.6,
      "lat": 42.653,
      "lon": -73.755
    }
  ],
  "daily_records": {
    "high": 101,
    "high_location": "Falcon Lake, TX (2022)",
    "low": -25,
    "low_location": "Embarrass, MN (1965)"
  },
  "stations_requested": 50,
  "stations_returned": 50,
  "stations_used": 50,
  "source": "Open-Meteo / WOPR Tactical"
}